FFmpyg/__init__.py
FFmpyg/command.py
FFmpyg/encoder_spec.py
FFmpyg/enums.py
FFmpyg/exceptions.py
FFmpyg/ffile.py
FFmpyg/ffmpeg_command.py
FFmpyg/ffmpeg_encoder.py
FFmpyg/ffmpeg_lib.py
FFmpyg/ffmpeg_vmaf.py
FFmpyg/ffprobe.py
FFmpyg/stream.py
FFmpyg/utils.py
FFmpyg/virtualfs.py
FFmpyg_DavidRodriguezSoaresCUI-0.0.6.dist-info/LICENSE
FFmpyg_DavidRodriguezSoaresCUI-0.0.6.dist-info/METADATA
FFmpyg_DavidRodriguezSoaresCUI-0.0.6.dist-info/WHEEL
FFmpyg_DavidRodriguezSoaresCUI-0.0.6.dist-info/top_level.txt
FFmpyg_DavidRodriguezSoaresCUI-0.0.6.dist-info/RECORD
