Metadata-Version: 2.1
Name: FFmpyg-DavidRodriguezSoaresCUI
Version: 0.0.6
Summary: A FFMPEG interface for Python by DavidRodriguezSoaresCUI
Author-email: DavidRodriguezSoaresCUI <fireblaze904+FFmpyg@gmail.com>
License: CC0 1.0 Universal
Project-URL: Homepage, https://github.com/DavidRodriguezSoaresCUI/FFmpyg
Project-URL: Bug Tracker, https://github.com/DavidRodriguezSoaresCUI/FFmpyg/issues
Classifier: Development Status :: 3 - Alpha
Classifier: Programming Language :: Python :: 3
Classifier: License :: CC0 1.0 Universal (CC0 1.0) Public Domain Dedication
Classifier: Operating System :: OS Independent
Requires-Python: >=3.7
License-File: LICENSE
